superparams/__init__.py
superparams/experiment.py
superparams/shared.py
superparams-0.1.0.dist-info/METADATA
superparams-0.1.0.dist-info/WHEEL
superparams-0.1.0.dist-info/entry_points.txt
superparams-0.1.0.dist-info/licenses/LICENSE
superparams-0.1.0.dist-info/RECORD
