Metadata-Version: 2.4
Name: superparams
Version: 0.1.0
Summary: Programmatic space search with a focus on flexibility
Project-URL: Homepage, https://github.com/Ar4l/superparams
Project-URL: Issues, https://github.com/Ar4l/superparams/issues
Author-email: Aral <me@aral.cc>
License-File: LICENSE
Classifier: License :: OSI Approved :: MIT License
Classifier: Operating System :: OS Independent
Classifier: Programming Language :: Python :: 3.11
Requires-Python: >=3.11
Requires-Dist: filelock>=3.16.1
Requires-Dist: multiprocess>=0.70.16
Requires-Dist: polars>=1.27.1
Provides-Extra: dev
Requires-Dist: pytest>=8.3.3; extra == 'dev'
Requires-Dist: uv>=0.4.28; extra == 'dev'
